<?xml version="1.0" encoding="utf-8" ?>
<Defs>

	<RecipeDef>
		<defName>PreciseVivisectionAlpha</defName>
		<label>Precise vivisection (alpha)</label>
		<description>Precise vivisection (alpha).</description>
		<jobString>conducts vivisection on alien creature</jobString>
		<recipeUsers>
			<li>PI_ContainmentBreach</li>
			<li>PI_ContainmentBreachAdv</li>
		</recipeUsers>
		<workAmount>300</workAmount>
		<workSpeedStat>GeneralLaborSpeed</workSpeedStat>
		<workSkill>Medicine</workSkill>
		<soundWorking>Recipe_ButcherCorpseFlesh</soundWorking>
		<products>
			<PI_PlasmaNucleus>1</PI_PlasmaNucleus>
			<PI_NervousSystem>1</PI_NervousSystem>
			<PI_Tentacles>6</PI_Tentacles>
			<PI_ToxicSac>1</PI_ToxicSac>
			<PI_AlphaBlood>10</PI_AlphaBlood>
		</products>
		<specialProducts>
			<li>Butchery</li>
		</specialProducts>
	</RecipeDef> 

	<RecipeDef>
		<defName>PreciseVivisectionBeta</defName>
		<label>Precise vivisection (beta)</label>
		<description>Precise vivisection (beta).</description>
		<jobString>conducts vivisection on alien creature</jobString>
		<recipeUsers>
			<li>PI_ContainmentBreach</li>
			<li>PI_ContainmentBreachAdv</li>
		</recipeUsers>
		<workAmount>300</workAmount>
		<workSpeedStat>GeneralLaborSpeed</workSpeedStat>
		<workSkill>Medicine</workSkill>
		<soundWorking>Recipe_ButcherCorpseFlesh</soundWorking>
		<products>
			<PI_PlasmaNucleus>1</PI_PlasmaNucleus>
			<PI_NervousSystem>1</PI_NervousSystem>
			<PI_Tentacles>6</PI_Tentacles>
			<PI_ToxicSac>1</PI_ToxicSac>
			<PI_BetaBlood>7</PI_BetaBlood>
		</products>
		<specialProducts>
			<li>Butchery</li>
		</specialProducts>
	</RecipeDef> 

	<RecipeDef>
		<defName>PreciseVivisectionGamma</defName>
		<label>Precise vivisection (gamma)</label>
		<description>Precise vivisection (gamma).</description>
		<jobString>conducts vivisection on alien creature</jobString>
		<recipeUsers>
			<li>PI_ContainmentBreach</li>
			<li>PI_ContainmentBreachAdv</li>
		</recipeUsers>
		<workAmount>300</workAmount>
		<workSpeedStat>GeneralLaborSpeed</workSpeedStat>
		<workSkill>Medicine</workSkill>
		<soundWorking>Recipe_ButcherCorpseFlesh</soundWorking>
		<products>
			<PI_PlasmaNucleus>1</PI_PlasmaNucleus>
			<PI_NervousSystem>1</PI_NervousSystem>
			<PI_Tentacles>6</PI_Tentacles>
			<PI_ToxicSac>1</PI_ToxicSac>
			<PI_GammaBlood>7</PI_GammaBlood>
		</products>
		<specialProducts>
			<li>Butchery</li>
		</specialProducts>
	</RecipeDef> 

	<RecipeDef>
		<defName>PreciseVivisectionOmega</defName>
		<label>Precise vivisection (omega)</label>
		<description>Precise vivisection (omega).</description>
		<jobString>conducts vivisection on alien creature</jobString>
		<recipeUsers>
			<li>PI_ContainmentBreach</li>
			<li>PI_ContainmentBreachAdv</li>
		</recipeUsers>
		<products>
			<PI_PlasmaNucleus>1</PI_PlasmaNucleus>
			<PI_NervousSystem>1</PI_NervousSystem>
			<PI_Tentacles>6</PI_Tentacles>
			<PI_ToxicSac>1</PI_ToxicSac>
			<PI_OmegaBlood>5</PI_OmegaBlood>
		</products>
		<workAmount>300</workAmount>
		<workSpeedStat>GeneralLaborSpeed</workSpeedStat>
		<workSkill>Medicine</workSkill>
		<soundWorking>Recipe_ButcherCorpseFlesh</soundWorking>
		<specialProducts>
			<li>Butchery</li>
		</specialProducts>
	</RecipeDef> 

</Defs>